{
  "fund_name": "ICICI Prudential Midcap Direct Plan-Growth",
  "scheme_name": "ICICI Prudential Midcap Direct Plan Growth",
  "fund_house": "ICICI Prudential Mutual Fund",
  "fund_manager": "Mrinal Singh, Mittul Kalawadia",
  "launch_date": "01-Jan-2013",
  "category": "Equity",
  "sub_category": "Mid Cap",
  "plan_type": "Direct",
  "scheme_type": "Growth",
  "isin": "INF109K011N7",
  "scheme_code": "120381",
  "description": "This scheme aims to generate long term capital appreciation by investing in diversified midcap stocks portfolio. It will predominantly invest in companies with market capitalization falling between the lowest and the highest market capitalisation among the constituents of Nifty Midcap 100 Index.",
  "nav": 382.14,
  "nav_date": "25-Jun-2026",
  "aum": 7789.34957998,
  "expense_ratio": "1.15",
  "exit_load": "Exit load of 1% if redeemed within 1 year.",
  "min_sip_investment": 100,
  "max_sip_investment": 200000,
  "min_investment_amount": 5000,
  "min_withdrawal": 0.01,
  "benchmark_name": "NIFTY Midcap 150 Total Return Index",
  "risk": "Moderately High",
  "groww_rating": 4,
  "sip_allowed": true,
  "lumpsum_allowed": false,
  "stamp_duty": "0.005% (from July 1st, 2020)",
  "holdings_top10": [
    {
      "company_name": "BSE Ltd",
      "allocation_percent": 5.3858027,
      "sector": "Financial"
    },
    {
      "company_name": "Multi Commodity Exchange Of India Ltd",
      "allocation_percent": 4.70278803,
      "sector": "Financial"
    },
    {
      "company_name": "Apar Industries Ltd",
      "allocation_percent": 4.60955175,
      "sector": "Diversified"
    },
    {
      "company_name": "Jindal Steel & Power Ltd",
      "allocation_percent": 4.31849535,
      "sector": "Materials"
    },
    {
      "company_name": "Hindustan Petroleum Corporation Ltd",
      "allocation_percent": 3.6828505,
      "sector": "Energy & Utilities"
    },
    {
      "company_name": "Muthoot Finance Ltd",
      "allocation_percent": 3.53845205,
      "sector": "Financial"
    },
    {
      "company_name": "APL Apollo Tubes Ltd",
      "allocation_percent": 3.37906133,
      "sector": "Industrials"
    },
    {
      "company_name": "PB Fintech Ltd",
      "allocation_percent": 3.07871148,
      "sector": "Financial"
    },
    {
      "company_name": "Kei Industries Ltd",
      "allocation_percent": 2.9556935,
      "sector": "Industrials"
    },
    {
      "company_name": "Bharat Forge Ltd",
      "allocation_percent": 2.95211297,
      "sector": "Consumer Discretionary"
    }
  ],
  "sector_allocation": [
    {
      "sector": "Financial",
      "allocation_percent": 16.7058
    },
    {
      "sector": "Industrials",
      "allocation_percent": 6.3348
    },
    {
      "sector": "Diversified",
      "allocation_percent": 4.6096
    },
    {
      "sector": "Materials",
      "allocation_percent": 4.3185
    },
    {
      "sector": "Energy & Utilities",
      "allocation_percent": 3.6829
    },
    {
      "sector": "Consumer Discretionary",
      "allocation_percent": 2.9521
    }
  ],
  "returns": {
    "returns_1y": 13.37,
    "returns_3y": 25.53,
    "returns_5y": 19.34,
    "returns_10y": null,
    "returns_since_launch": 18.64
  },
  "category_returns": {
    "category_avg_1y": 1.9589569430918827,
    "category_avg_3y": 21.621655585469462,
    "category_avg_5y": 21.52750809939988
  },
  "fund_manager_details": [
    {
      "name": "Sharmila D'Silva",
      "start_date": "2022-06-30T18:30:00.000Z",
      "qualification": "Ms. D'Silva is CA and BAF"
    },
    {
      "name": "Lalit Kumar",
      "start_date": "2022-08-07T18:30:00.000Z",
      "qualification": "Mr. Kumar is a PGDM (IIM) and B.Tech in Electrical Engineering (IIT)."
    }
  ],
  "exit_load_details": {
    "exit_load_text": "Exit load of 1% if redeemed within 1 year.",
    "exit_load_history": [
      {
        "note": "Exit load of 1% if redeemed within 1 year.",
        "as_on_date": "2015-05-18T00:00:00"
      },
      {
        "note": "Exit load of 1% if redeemed within 18 months",
        "as_on_date": "2014-04-15T00:00:00"
      },
      {
        "note": "Exit load of 1% if redeemed upto 1 year",
        "as_on_date": "2013-01-01T00:00:00"
      }
    ]
  },
  "lock_in_period": {
    "lock_in_years": null,
    "lock_in_months": null,
    "lock_in_days": null
  },
  "_metadata": {
    "scheme_id": "icici-prudential-midcap",
    "source_url": "https://groww.in/mutual-funds/icici-prudential-midcap-fund-direct-growth",
    "scrape_timestamp": "2026-06-26T04:54:23.542882Z",
    "data_source": "__NEXT_DATA__",
    "extractor_version": "1.0.0"
  }
}